LICENSE
README.md
dist.json
setup.py
lib/envstack/__init__.py
lib/envstack/cli.py
lib/envstack/config.py
lib/envstack/encrypt.py
lib/envstack/env.py
lib/envstack/envshell.py
lib/envstack/exceptions.py
lib/envstack/logger.py
lib/envstack/node.py
lib/envstack/path.py
lib/envstack/util.py
lib/envstack/wrapper.py
lib/envstack.egg-info/PKG-INFO
lib/envstack.egg-info/SOURCES.txt
lib/envstack.egg-info/dependency_links.txt
lib/envstack.egg-info/entry_points.txt
lib/envstack.egg-info/not-zip-safe
lib/envstack.egg-info/requires.txt
lib/envstack.egg-info/top_level.txt
tests/test_cmds.py
tests/test_encrypt.py
tests/test_env.py
tests/test_node.py
tests/test_util.py