Metadata-Version: 2.1
Name: envstack
Version: 0.9.3
Summary: Stacked environment variable management system
Home-page: http://github.com/rsgalloway/envstack
Author: Ryan Galloway
Author-email: ryan@rsgalloway.com
License: BSD 3-Clause License
Classifier: Development Status :: 4 - Beta
Classifier: Intended Audience :: Developers
Classifier: Topic :: Software Development :: Libraries
Classifier: Programming Language :: Python :: 3
Classifier: Programming Language :: Python :: 3.6
Classifier: Programming Language :: Python :: 3.7
Classifier: Programming Language :: Python :: 3.8
Classifier: Programming Language :: Python :: 3.9
Classifier: Programming Language :: Python :: 3.10
Classifier: Programming Language :: Python :: 3.11
Requires-Python: >=3.6
License-File: LICENSE
Requires-Dist: PyYAML>=5.1.2
Requires-Dist: cryptography>=43.0.1
